README.rst
citylink.py
setup.cfg
setup.py
citylink_utils.egg-info/PKG-INFO
citylink_utils.egg-info/SOURCES.txt
citylink_utils.egg-info/dependency_links.txt
citylink_utils.egg-info/requires.txt
citylink_utils.egg-info/top_level.txt