Metadata-Version: 1.1
Name: citylink-utils
Version: 0.8b
Summary: Simple utility package to handle CityLink dispatches for commercial customers
Home-page: https://github.com/OdinsHat/citylink-utils
Author: Doug Bromley
Author-email: doug+clutils@tintophat.com
License: BSD
Keywords: citylink courier web scraping
Platform: any
Classifier: License :: OSI Approved :: BSD License
Classifier: Development Status :: 3 - BetaOperating System :: POSIX :: Linux
Classifier: Intended Audience :: Developers
Classifier: Programming Language :: Python
Classifier: Programming Language :: Python :: 2.5
Classifier: Programming Language :: Python :: 2.6
Classifier: Programming Language :: Python :: 2.7
Classifier: Programming Language :: Python :: 3
Classifier: Topic :: Software Development :: Libraries :: Python Modules
Classifier: Topic :: Text Processing :: Markup :: HTML
